giszhao/__init__.py
giszhao/common.py
giszhao/giszhao.py
giszhao-0.0.2.dist-info/LICENSE
giszhao-0.0.2.dist-info/METADATA
giszhao-0.0.2.dist-info/WHEEL
giszhao-0.0.2.dist-info/top_level.txt
giszhao-0.0.2.dist-info/RECORD
