Metadata-Version: 2.1
Name: giszhao
Version: 0.0.2
Summary: This is a test pkg from Yun Zhao in Summer 2023.
Home-page: https://github.com/zhaoyun1230/giszhao
Author: Yun Zhao
Author-email: zhaoyun1230@gmail.com
License: MIT license
Keywords: giszhao
Classifier: Intended Audience :: Developers
Classifier: License :: OSI Approved :: MIT License
Classifier: Natural Language :: English
Classifier: Programming Language :: Python :: 3
Classifier: Programming Language :: Python :: 3.8
Classifier: Programming Language :: Python :: 3.9
Classifier: Programming Language :: Python :: 3.10
Classifier: Programming Language :: Python :: 3.11
Requires-Python: >=3.8
License-File: LICENSE
